Metadata-Version: 2.1
Name: odoo10-addon-hr-emergency-contact
Version: 10.0.1.0.0.99.dev13
Summary: HR Emergency Contact
Home-page: http://www.openerp.com
Author: OpenSynergy Indonesia,Michael Telahun Makonnen,Odoo Community Association (OCA)
Author-email: support@odoo-community.org
License: AGPL-3
Platform: UNKNOWN
Classifier: Programming Language :: Python
Classifier: Framework :: Odoo
Classifier: License :: OSI Approved :: GNU Affero General Public License v3
Requires-Python: ~=2.7
Requires-Dist: odoo (<10.1dev,>=10.0)
